odoo9_addon_project_stage_closed-9.0.1.0.0-py2.7-nspkg.pth
odoo9_addon_project_stage_closed-9.0.1.0.0.dist-info/top_level.txt
odoo9_addon_project_stage_closed-9.0.1.0.0.dist-info/WHEEL
odoo9_addon_project_stage_closed-9.0.1.0.0.dist-info/RECORD
odoo9_addon_project_stage_closed-9.0.1.0.0.dist-info/metadata.json
odoo9_addon_project_stage_closed-9.0.1.0.0.dist-info/DESCRIPTION.rst
odoo9_addon_project_stage_closed-9.0.1.0.0.dist-info/METADATA
odoo9_addon_project_stage_closed-9.0.1.0.0.dist-info/namespace_packages.txt
odoo_addons/project_stage_closed/__openerp__.py
odoo_addons/project_stage_closed/__init__.py
odoo_addons/project_stage_closed/README.rst
odoo_addons/project_stage_closed/models/__init__.py
odoo_addons/project_stage_closed/models/task_stage.py
odoo_addons/project_stage_closed/i18n/pt.po
odoo_addons/project_stage_closed/i18n/es.po
odoo_addons/project_stage_closed/i18n/sl.po
odoo_addons/project_stage_closed/i18n/pt_PT.po
odoo_addons/project_stage_closed/i18n/nb.po
odoo_addons/project_stage_closed/i18n/de.po
odoo_addons/project_stage_closed/i18n/fr.po
odoo_addons/project_stage_closed/i18n/pt_BR.po
odoo_addons/project_stage_closed/i18n/sv.po
odoo_addons/project_stage_closed/i18n/fi.po
odoo_addons/project_stage_closed/views/task_stage.xml
odoo_addons/project_stage_closed/tests/__init__.py
odoo_addons/project_stage_closed/tests/test_project_stage_closed.py
odoo_addons/project_stage_closed/static/description/icon.png
